ultimatethumb/__init__.py
ultimatethumb/commands.py
ultimatethumb/storage.py
ultimatethumb/templatetags/__init__.py
ultimatethumb/templatetags/ultimatethumb_tags.py
ultimatethumb/thumbnail.py
ultimatethumb/urls.py
ultimatethumb/utils.py
ultimatethumb/views.py
django_ultimatethumb-1.4.0.dist-info/LICENSE.rst
django_ultimatethumb-1.4.0.dist-info/METADATA
django_ultimatethumb-1.4.0.dist-info/WHEEL
django_ultimatethumb-1.4.0.dist-info/RECORD
