Metadata-Version: 2.3
Name: django-ultimatethumb
Version: 1.4.0
Summary: Generate thumbnails of anything.
License: BSD-3-Clause
Author: Stephan Jaekel
Author-email: steph@rdev.info
Requires-Python: >=3.8,<4
Classifier: Development Status :: 4 - Beta
Classifier: Environment :: Web Environment
Classifier: Framework :: Django
Classifier: Intended Audience :: Developers
Classifier: License :: OSI Approved :: BSD License
Classifier: Operating System :: Unix
Classifier: Programming Language :: Python
Classifier: Programming Language :: Python :: 3
Classifier: Programming Language :: Python :: 3.8
Classifier: Programming Language :: Python :: 3.9
Classifier: Programming Language :: Python :: 3.10
Classifier: Programming Language :: Python :: 3.11
Classifier: Programming Language :: Python :: 3.12
Classifier: Programming Language :: Python :: 3.13
Provides-Extra: docs
Requires-Dist: Django (>=2.2)
Requires-Dist: Pillow (>=8.3)
Requires-Dist: Sphinx (>=3.5) ; extra == "docs"
Requires-Dist: command_executor (>=0.1)
Project-URL: Homepage, https://github.com/stephrdev/django-ultimatethumb
Project-URL: Repository, https://github.com/stephrdev/django-ultimatethumb
